fleeks_sdk/__init__.py
fleeks_sdk/agents.py
fleeks_sdk/auth.py
fleeks_sdk/client.py
fleeks_sdk/config.py
fleeks_sdk/containers.py
fleeks_sdk/exceptions.py
fleeks_sdk/files.py
fleeks_sdk/models.py
fleeks_sdk/streaming.py
fleeks_sdk/terminal.py
fleeks_sdk/workspaces.py
fleeks_sdk-0.2.7.dist-info/licenses/LICENSE
fleeks_sdk-0.2.7.dist-info/METADATA
fleeks_sdk-0.2.7.dist-info/WHEEL
fleeks_sdk-0.2.7.dist-info/top_level.txt
fleeks_sdk-0.2.7.dist-info/RECORD
