Metadata-Version: 2.4
Name: fleeks-sdk
Version: 0.2.7
Summary: Python SDK for Fleeks services
Author-email: Fleeks Inc <support@fleeks.com>
License-Expression: MIT
Project-URL: Homepage, https://fleeks.ai
Project-URL: Documentation, https://docs.fleeks.ai
Project-URL: Repository, https://github.com/fleeks-ai/fleeks-sdk-python
Project-URL: Bug Tracker, https://github.com/fleeks-ai/fleeks-sdk-python/issues
Project-URL: Source Code, https://github.com/fleeks-ai/fleeks-sdk-python
Keywords: fleeks,sdk,development,workspaces,containers,ai,agents
Classifier: Development Status :: 3 - Alpha
Classifier: Intended Audience :: Developers
Classifier: Programming Language :: Python :: 3
Classifier: Programming Language :: Python :: 3.9
Classifier: Programming Language :: Python :: 3.10
Classifier: Programming Language :: Python :: 3.11
Classifier: Programming Language :: Python :: 3.12
Classifier: Topic :: Software Development :: Libraries :: Python Modules
Classifier: Topic :: Internet :: WWW/HTTP :: HTTP Servers
Requires-Python: >=3.9
License-File: LICENSE
Requires-Dist: httpx>=0.25.0
Requires-Dist: python-socketio[asyncio]>=5.8.0
Requires-Dist: pydantic>=2.0.0
Requires-Dist: python-dotenv>=1.0.0
Requires-Dist: tenacity>=8.2.0
Requires-Dist: typing-extensions>=4.0.0
Provides-Extra: dev
Requires-Dist: pytest>=7.0; extra == "dev"
Requires-Dist: pytest-asyncio>=0.21.0; extra == "dev"
Requires-Dist: pytest-cov>=4.0; extra == "dev"
Requires-Dist: black>=23.0; extra == "dev"
Requires-Dist: flake8>=6.0; extra == "dev"
Requires-Dist: mypy>=1.0; extra == "dev"
Requires-Dist: isort>=5.0; extra == "dev"
Requires-Dist: pre-commit>=3.0; extra == "dev"
Requires-Dist: httpx-mock>=0.10.0; extra == "dev"
Provides-Extra: docs
Requires-Dist: sphinx>=4.0; extra == "docs"
Requires-Dist: sphinx-rtd-theme>=1.0; extra == "docs"
Dynamic: license-file
